del_msh_numpy-0.1.43.dist-info/METADATA
del_msh_numpy-0.1.43.dist-info/WHEEL
del_msh_numpy/BVH.py
del_msh_numpy/BlendShape.py
del_msh_numpy/DeformMLS.py
del_msh_numpy/KdTree.py
del_msh_numpy/PolyLoop.py
del_msh_numpy/PolygonMesh.py
del_msh_numpy/Polyline.py
del_msh_numpy/Tet.py
del_msh_numpy/Tri.py
del_msh_numpy/TriMesh.py
del_msh_numpy/WavefrontObj.py
del_msh_numpy/__init__.py
del_msh_numpy/del_msh_numpy.cpython-312-darwin.so
del_msh_numpy-0.1.43.dist-info/RECORD
